{
  "article_number": "AOP858",
  "article_id": 32148885,
  "product_name": "Oil Pump",
  "oem_numbers": [
    "C2Z28368",
    "DW936600BA",
    "LR052436"
  ],
  "specifications": [],
  "engine_codes": [
    "508PS(AJ133)",
    "508PN(AJ133)",
    "306PS(AJ126)",
    "FG(AJV6)",
    "PT306(AJ20P6)"
  ],
  "compatibility_rows": [
    {
      "vehicle": "JAGUAR XJ (X351) 5.0 SCV8",
      "production_years": "2009-10 to 2019-12",
      "kw": "346",
      "hp": "471",
      "cc": "5000",
      "engine_codes": [
        "508PS(AJ133)"
      ],
      "k_number": "1029"
    },
    {
      "vehicle": "JAGUAR XK II Coupe (X150) 5.0 XKR-S",
      "production_years": "2011-01 to 2014-07",
      "kw": "405",
      "hp": "550",
      "cc": "5000",
      "engine_codes": [
        "508PS(AJ133)"
      ],
      "k_number": "9334"
    },
    {
      "vehicle": "JAGUAR XK II Coupe (X150) 5.0 XKR",
      "production_years": "2010-09 to 2014-07",
      "kw": "390",
      "hp": "530",
      "cc": "5000",
      "engine_codes": [
        "508PS(AJ133)"
      ],
      "k_number": "9336"
    },
    {
      "vehicle": "JAGUAR XF I (X250) 5.0 Kompressor",
      "production_years": "2009-01 to 2015-04",
      "kw": "346",
      "hp": "471",
      "cc": "5000",
      "engine_codes": [
        "508PS(AJ133)"
      ],
      "k_number": "10931"
    },
    {
      "vehicle": "JAGUAR XK II Convertible (X150) 5.0 XKR-S",
      "production_years": "2011-01 to 2014-07",
      "kw": "405",
      "hp": "550",
      "cc": "5000",
      "engine_codes": [
        "508PS(AJ133)"
      ],
      "k_number": "11249"
    },
    {
      "vehicle": "JAGUAR XJ (X351) 5.0 SCV8",
      "production_years": "2013-06 to 2019-12",
      "kw": "405",
      "hp": "550",
      "cc": "5000",
      "engine_codes": [
        "508PS(AJ133)"
      ],
      "k_number": "24106"
    },
    {
      "vehicle": "JAGUAR XF I (X250) 5.0 Kompressor",
      "production_years": "2009-03 to 2015-04",
      "kw": "375",
      "hp": "510",
      "cc": "5000",
      "engine_codes": [
        "508PS(AJ133)"
      ],
      "k_number": "31363"
    },
    {
      "vehicle": "JAGUAR XK II Convertible (X150) 5.0 XKR",
      "production_years": "2009-01 to 2014-07",
      "kw": "375",
      "hp": "510",
      "cc": "5000",
      "engine_codes": [
        "508PS(AJ133)"
      ],
      "k_number": "31401"
    },
    {
      "vehicle": "JAGUAR XK II Coupe (X150) 5.0 XKR",
      "production_years": "2009-01 to 2014-07",
      "kw": "375",
      "hp": "510",
      "cc": "5000",
      "engine_codes": [
        "508PS(AJ133)"
      ],
      "k_number": "31403"
    },
    {
      "vehicle": "JAGUAR XJ (X351) 5.0 SCV8",
      "production_years": "2009-10 to 2019-12",
      "kw": "375",
      "hp": "510",
      "cc": "5000",
      "engine_codes": [
        "508PS(AJ133)"
      ],
      "k_number": "34770"
    },
    {
      "vehicle": "JAGUAR F-TYPE Convertible (X152) 5.0 SCV8 S",
      "production_years": "2012-10 to Onwards",
      "kw": "364",
      "hp": "495",
      "cc": "5000",
      "engine_codes": [
        "508PS(AJ133)"
      ],
      "k_number": "57134"
    },
    {
      "vehicle": "JAGUAR XF I (X250) 5.0 XFR-S",
      "production_years": "2012-10 to 2015-04",
      "kw": "405",
      "hp": "550",
      "cc": "5000",
      "engine_codes": [
        "508PS(AJ133)"
      ],
      "k_number": "57474"
    },
    {
      "vehicle": "JAGUAR F-TYPE Coupe (X152) 5.0 SCV8 R",
      "production_years": "2013-10 to Onwards",
      "kw": "405",
      "hp": "551",
      "cc": "5000",
      "engine_codes": [
        "508PS(AJ133)"
      ],
      "k_number": "100688"
    },
    {
      "vehicle": "JAGUAR XF SPORTBRAKE (X250) 5.0 XFR-S",
      "production_years": "2013-02 to 2014-04",
      "kw": "405",
      "hp": "550",
      "cc": "5000",
      "engine_codes": [
        "508PS(AJ133)"
      ],
      "k_number": "101018"
    },
    {
      "vehicle": "JAGUAR F-TYPE Coupe (X152) 5.0 SCV8 R AWD",
      "production_years": "2014-12 to Onwards",
      "kw": "405",
      "hp": "551",
      "cc": "5000",
      "engine_codes": [
        "508PS(AJ133)"
      ],
      "k_number": "109351"
    },
    {
      "vehicle": "JAGUAR F-TYPE Convertible (X152) 5.0 SCV8 R",
      "production_years": "2013-10 to Onwards",
      "kw": "405",
      "hp": "551",
      "cc": "5000",
      "engine_codes": [
        "508PS(AJ133)"
      ],
      "k_number": "109352"
    },
    {
      "vehicle": "JAGUAR F-TYPE Convertible (X152) 5.0 SCV8 R AWD",
      "production_years": "2014-12 to Onwards",
      "kw": "405",
      "hp": "551",
      "cc": "5000",
      "engine_codes": [
        "508PS(AJ133)"
      ],
      "k_number": "109353"
    },
    {
      "vehicle": "JAGUAR F-TYPE Convertible (X152) 5.0 SCV8 SVR / SCV8 P575 R AWD",
      "production_years": "2015-12 to Onwards",
      "kw": "423",
      "hp": "575",
      "cc": "5000",
      "engine_codes": [
        "508PS(AJ133)"
      ],
      "k_number": "117709"
    },
    {
      "vehicle": "JAGUAR F-TYPE Coupe (X152) 5.0 SCV8 SVR / SCV8 P575 R",
      "production_years": "2015-12 to Onwards",
      "kw": "423",
      "hp": "575",
      "cc": "5000",
      "engine_codes": [
        "508PS(AJ133)"
      ],
      "k_number": "118546"
    },
    {
      "vehicle": "JAGUAR XJ (X351) 5.0 SCV8 R575",
      "production_years": "2017-06 to 2019-12",
      "kw": "423",
      "hp": "575",
      "cc": "5000",
      "engine_codes": [
        "508PS(AJ133)"
      ],
      "k_number": "128571"
    },
    {
      "vehicle": "JAGUAR F-TYPE Convertible (X152) 5.0 SCV8 SVR",
      "production_years": "2015-05 to Onwards",
      "kw": "423",
      "hp": "575",
      "cc": "5000",
      "engine_codes": [
        "508PS(AJ133)"
      ],
      "k_number": "129271"
    },
    {
      "vehicle": "JAGUAR XF I (X250) 5.0 Kompressor",
      "production_years": "2013-01 to 2015-04",
      "kw": "380",
      "hp": "517",
      "cc": "5000",
      "engine_codes": [
        "508PS(AJ133)"
      ],
      "k_number": "132006"
    },
    {
      "vehicle": "JAGUAR F-TYPE Convertible (X152) 5.0 SCV8 P450",
      "production_years": "2019-12 to Onwards",
      "kw": "331",
      "hp": "450",
      "cc": "5000",
      "engine_codes": [
        "508PS(AJ133)"
      ],
      "k_number": "139188"
    },
    {
      "vehicle": "JAGUAR F-TYPE Convertible (X152) 5.0 SCV8 P450 AWD",
      "production_years": "2019-12 to Onwards",
      "kw": "331",
      "hp": "450",
      "cc": "5000",
      "engine_codes": [
        "508PS(AJ133)"
      ],
      "k_number": "139190"
    },
    {
      "vehicle": "JAGUAR F-TYPE Coupe (X152) 5.0 SCV8 P450",
      "production_years": "2019-12 to Onwards",
      "kw": "331",
      "hp": "450",
      "cc": "5000",
      "engine_codes": [
        "508PS(AJ133)"
      ],
      "k_number": "139191"
    },
    {
      "vehicle": "JAGUAR F-TYPE Coupe (X152) 5.0 SCV8 P450 AWD",
      "production_years": "2019-12 to Onwards",
      "kw": "331",
      "hp": "450",
      "cc": "5000",
      "engine_codes": [
        "508PS(AJ133)"
      ],
      "k_number": "139193"
    },
    {
      "vehicle": "LAND ROVER RANGE ROVER III (L322) 5.0 4x4",
      "production_years": "2009-09 to 2012-08",
      "kw": "276",
      "hp": "375",
      "cc": "4999",
      "engine_codes": [
        "508PN(AJ133)"
      ],
      "k_number": "2534"
    },
    {
      "vehicle": "LAND ROVER DISCOVERY IV (L319) 5.0 V8 4x4",
      "production_years": "2009-09 to 2018-12",
      "kw": "276",
      "hp": "375",
      "cc": "4999",
      "engine_codes": [
        "508PN(AJ133)"
      ],
      "k_number": "2940"
    },
    {
      "vehicle": "LAND ROVER RANGE ROVER SPORT I (L320) 5.0 4x4",
      "production_years": "2009-07 to 2013-03",
      "kw": "276",
      "hp": "375",
      "cc": "4999",
      "engine_codes": [
        "508PN(AJ133)"
      ],
      "k_number": "3113"
    },
    {
      "vehicle": "LAND ROVER RANGE ROVER IV (L405) 5.0 V8 4x4",
      "production_years": "2013-12 to 2016-01",
      "kw": "276",
      "hp": "375",
      "cc": "5000",
      "engine_codes": [
        "508PN(AJ133)"
      ],
      "k_number": "100503"
    },
    {
      "vehicle": "LAND ROVER RANGE ROVER SPORT I (L320) 5.0 4x4",
      "production_years": "2009-04 to 2013-03",
      "kw": "372",
      "hp": "506",
      "cc": "4999",
      "engine_codes": [
        "508PS(AJ133)"
      ],
      "k_number": "4718"
    },
    {
      "vehicle": "LAND ROVER RANGE ROVER III (L322) 5.0 4x4",
      "production_years": "2009-09 to 2012-08",
      "kw": "375",
      "hp": "510",
      "cc": "4999",
      "engine_codes": [
        "508PS(AJ133)"
      ],
      "k_number": "32051"
    },
    {
      "vehicle": "LAND ROVER RANGE ROVER SPORT I (L320) 5.0 4x4",
      "production_years": "2009-09 to 2013-03",
      "kw": "375",
      "hp": "510",
      "cc": "4999",
      "engine_codes": [
        "508PS(AJ133)"
      ],
      "k_number": "32052"
    },
    {
      "vehicle": "LAND ROVER RANGE ROVER IV (L405) 5.0 SCV8 4x4",
      "production_years": "2012-08 to 2021-09",
      "kw": "375",
      "hp": "510",
      "cc": "5000",
      "engine_codes": [
        "508PS(AJ133)"
      ],
      "k_number": "57067"
    },
    {
      "vehicle": "LAND ROVER RANGE ROVER IV (L405) 5.0 SCV8 4x4",
      "production_years": "2015-06 to 2021-09",
      "kw": "405",
      "hp": "550",
      "cc": "5000",
      "engine_codes": [
        "508PS(AJ133)"
      ],
      "k_number": "115836"
    },
    {
      "vehicle": "LAND ROVER RANGE ROVER IV (L405) 5.0 SCV8 4x4",
      "production_years": "2017-11 to 2021-09",
      "kw": "386",
      "hp": "525",
      "cc": "5000",
      "engine_codes": [
        "508PS(AJ133)"
      ],
      "k_number": "129783"
    },
    {
      "vehicle": "LAND ROVER RANGE ROVER IV (L405) 5.0 SCV8 4x4",
      "production_years": "2017-11 to 2021-09",
      "kw": "416",
      "hp": "566",
      "cc": "5000",
      "engine_codes": [
        "508PS(AJ133)"
      ],
      "k_number": "129784"
    },
    {
      "vehicle": "LAND ROVER RANGE ROVER IV (L405) SCV8 4x4",
      "production_years": "2019-01 to 2021-09",
      "kw": "415",
      "hp": "565",
      "cc": "5000",
      "engine_codes": [
        "508PS(AJ133)"
      ],
      "k_number": "138973"
    },
    {
      "vehicle": "LAND ROVER DISCOVERY IV (L319) 3.0 4x4",
      "production_years": "2013-08 to 2018-12",
      "kw": "250",
      "hp": "340",
      "cc": "2995",
      "engine_codes": [
        "306PS(AJ126)"
      ],
      "k_number": "9312"
    },
    {
      "vehicle": "LAND ROVER RANGE ROVER IV (L405) 3.0 SCV6 4x4",
      "production_years": "2013-10 to 2021-09",
      "kw": "250",
      "hp": "340",
      "cc": "2995",
      "engine_codes": [
        "306PS(AJ126)"
      ],
      "k_number": "100015"
    },
    {
      "vehicle": "LAND ROVER RANGE ROVER IV (L405) 3.0 SCV6 4x4",
      "production_years": "2015-06 to 2016-01",
      "kw": "280",
      "hp": "380",
      "cc": "2995",
      "engine_codes": [
        "306PS(AJ126)"
      ],
      "k_number": "115843"
    },
    {
      "vehicle": "JAGUAR XF I (X250) 3.0",
      "production_years": "2008-03 to 2015-04",
      "kw": "175",
      "hp": "238",
      "cc": "2967",
      "engine_codes": [
        "FG(AJV6)"
      ],
      "k_number": "24474"
    },
    {
      "vehicle": "JAGUAR XF I (X250) 5.0",
      "production_years": "2009-03 to 2015-04",
      "kw": "283",
      "hp": "385",
      "cc": "5000",
      "engine_codes": [
        "508PN(AJ133)"
      ],
      "k_number": "31362"
    },
    {
      "vehicle": "JAGUAR XJ (X351) 5.0 V8",
      "production_years": "2009-10 to 2019-12",
      "kw": "283",
      "hp": "385",
      "cc": "5000",
      "engine_codes": [
        "508PN(AJ133)"
      ],
      "k_number": "33886"
    },
    {
      "vehicle": "JAGUAR XK II Coupe (X150) 5.0 V8",
      "production_years": "2009-01 to 2014-07",
      "kw": "283",
      "hp": "385",
      "cc": "5000",
      "engine_codes": [
        "508PN(AJ133)"
      ],
      "k_number": "34772"
    },
    {
      "vehicle": "JAGUAR XK II Convertible (X150) 5.0 V8",
      "production_years": "2009-01 to 2014-07",
      "kw": "283",
      "hp": "385",
      "cc": "5000",
      "engine_codes": [
        "508PN(AJ133)"
      ],
      "k_number": "34773"
    },
    {
      "vehicle": "JAGUAR XJ (X351) 5.0 V8",
      "production_years": "2012-08 to 2019-12",
      "kw": "287",
      "hp": "390",
      "cc": "5000",
      "engine_codes": [
        "508PN(AJ133)"
      ],
      "k_number": "124392"
    },
    {
      "vehicle": "JAGUAR XF I (X250) 3.0",
      "production_years": "2012-03 to 2015-04",
      "kw": "250",
      "hp": "340",
      "cc": "2995",
      "engine_codes": [
        "306PS(AJ126)"
      ],
      "k_number": "55990"
    },
    {
      "vehicle": "JAGUAR XJ (X351) 3.0 SCV6",
      "production_years": "2012-03 to 2019-12",
      "kw": "250",
      "hp": "340",
      "cc": "2995",
      "engine_codes": [
        "306PS(AJ126)"
      ],
      "k_number": "56001"
    },
    {
      "vehicle": "JAGUAR XF I (X250) 3.0 AWD",
      "production_years": "2012-10 to 2015-04",
      "kw": "250",
      "hp": "340",
      "cc": "2995",
      "engine_codes": [
        "306PS(AJ126)"
      ],
      "k_number": "58152"
    },
    {
      "vehicle": "JAGUAR XJ (X351) 3.0 SCV6 AWD",
      "production_years": "2012-10 to 2019-12",
      "kw": "250",
      "hp": "340",
      "cc": "2995",
      "engine_codes": [
        "306PS(AJ126)"
      ],
      "k_number": "58153"
    },
    {
      "vehicle": "JAGUAR F-TYPE Convertible (X152) 3.0 SCV6",
      "production_years": "2012-10 to Onwards",
      "kw": "250",
      "hp": "340",
      "cc": "2995",
      "engine_codes": [
        "306PS(AJ126)"
      ],
      "k_number": "57131"
    },
    {
      "vehicle": "JAGUAR F-TYPE Convertible (X152) 3.0 SCV6 S",
      "production_years": "2012-10 to Onwards",
      "kw": "280",
      "hp": "380",
      "cc": "2995",
      "engine_codes": [
        "306PS(AJ126)"
      ],
      "k_number": "57133"
    },
    {
      "vehicle": "JAGUAR F-TYPE Coupe (X152) 3.0 SCV6",
      "production_years": "2013-10 to Onwards",
      "kw": "250",
      "hp": "340",
      "cc": "2995",
      "engine_codes": [
        "306PS(AJ126)"
      ],
      "k_number": "100686"
    },
    {
      "vehicle": "JAGUAR F-TYPE Coupe (X152) 3.0 SCV6 S",
      "production_years": "2013-10 to Onwards",
      "kw": "280",
      "hp": "380",
      "cc": "2995",
      "engine_codes": [
        "306PS(AJ126)"
      ],
      "k_number": "100687"
    },
    {
      "vehicle": "JAGUAR F-TYPE Convertible (X152) 3.0 SCV6 S AWD",
      "production_years": "2014-12 to Onwards",
      "kw": "280",
      "hp": "380",
      "cc": "2995",
      "engine_codes": [
        "306PS(AJ126)"
      ],
      "k_number": "109349"
    },
    {
      "vehicle": "JAGUAR F-TYPE Coupe (X152) 3.0 SCV6 S AWD",
      "production_years": "2014-12 to Onwards",
      "kw": "280",
      "hp": "380",
      "cc": "2995",
      "engine_codes": [
        "306PS(AJ126)"
      ],
      "k_number": "109350"
    },
    {
      "vehicle": "LAND ROVER RANGE ROVER IV (L405) 3.0 P400 4x4",
      "production_years": "2020-07 to 2021-09",
      "kw": "294",
      "hp": "400",
      "cc": "2996",
      "engine_codes": [
        "PT306(AJ20P6)"
      ],
      "k_number": "142095"
    }
  ]
}